bestnlp/__init__.py
bestnlp/dict.txt
bestnlp/new_word_discovery.py
bestnlp/similar_word_discovery.py
bestnlp/similar_word_discovery_embedding.py
bestnlp/utils.py
bestnlp-1.1.2.dist-info/METADATA
bestnlp-1.1.2.dist-info/WHEEL
bestnlp-1.1.2.dist-info/top_level.txt
bestnlp-1.1.2.dist-info/RECORD
