Metadata-Version: 2.1
Name: bestnlp
Version: 1.1.2
Summary: version
Home-page: https://pypi.org/project/bestnlp
Author: huyi
Author-email: cracks@yeah.net
Requires-Python: >=3.6.0
Requires-Dist: jieba (==0.42.1)
Requires-Dist: pandas (==1.3.5)
